anywidget_3dviewer/__init__.py
anywidget_3dviewer/static/viewer.js
anywidget_3dviewer/static/textures/JUPITER_baseColor.png
anywidget_3dviewer-0.0.2.dist-info/METADATA
anywidget_3dviewer-0.0.2.dist-info/WHEEL
anywidget_3dviewer-0.0.2.dist-info/licenses/LICENSE
anywidget_3dviewer-0.0.2.dist-info/RECORD
