Metadata-Version: 2.1
Name: anywidget_3dviewer
Version: 0.0.2
License-File: LICENSE
Requires-Dist: anywidget
Provides-Extra: dev
Requires-Dist: jupyterlab; extra == 'dev'
Requires-Dist: watchfiles; extra == 'dev'
